PriorKnowledgeNeuralODE/__init__.py
PriorKnowledgeNeuralODE/adaptiveFuncs.py
PriorKnowledgeNeuralODE-1.0.6.1.dist-info/LICENSE.txt
PriorKnowledgeNeuralODE-1.0.6.1.dist-info/METADATA
PriorKnowledgeNeuralODE-1.0.6.1.dist-info/WHEEL
PriorKnowledgeNeuralODE-1.0.6.1.dist-info/top_level.txt
PriorKnowledgeNeuralODE-1.0.6.1.dist-info/RECORD
